README.md
setup.py
gh_pr_comment/__init__.py
gh_pr_comment/comment.py
gh_pr_comment/upload.py
gh_pr_comment.egg-info/PKG-INFO
gh_pr_comment.egg-info/SOURCES.txt
gh_pr_comment.egg-info/dependency_links.txt
gh_pr_comment.egg-info/entry_points.txt
gh_pr_comment.egg-info/requires.txt
gh_pr_comment.egg-info/top_level.txt