Metadata-Version: 1.0
Name: gh-pr-comment
Version: 0.3.0
Summary: GitHub PR comment post
Home-page: https://github.com/at-wat/gh-pr-comment
Author: Atsushi Watanabe
Author-email: atsushi.w@ieee.org
License: BSD
Platform: UNKNOWN
